dashing/__init__.py
dashing/__main__.py
dashing/dashing.py
pydashing-1.0.0.dist-info/DESCRIPTION.rst
pydashing-1.0.0.dist-info/METADATA
pydashing-1.0.0.dist-info/RECORD
pydashing-1.0.0.dist-info/WHEEL
pydashing-1.0.0.dist-info/metadata.json
pydashing-1.0.0.dist-info/top_level.txt
