Metadata-Version: 2.0
Name: pydashing
Version: 1.0.0
Summary: High-level terminal-based dashboard
Home-page: https://github.com/chrismaille/dashing
Author: Chris Maillefaud
Author-email: chris@megalus.com.br
License: LGPL
Keywords: dashboard terminal
Platform: UNKNOWN
Classifier: Development Status :: 4 - Beta
Classifier: Environment :: Console
Classifier: Intended Audience :: Developers
Classifier: Programming Language :: Python :: 3.5
Classifier: Programming Language :: Python :: 3.6
Requires-Dist: blessed
Requires-Dist: buzio
